paindrop/__init__.py
paindrop/__main__.py
paindrop-1.0.0.dist-info/METADATA
paindrop-1.0.0.dist-info/WHEEL
paindrop-1.0.0.dist-info/entry_points.txt
paindrop-1.0.0.dist-info/licenses/LICENSE
paindrop-1.0.0.dist-info/RECORD
