Metadata-Version: 2.3
Name: paindrop
Version: 1.0.0
Summary: A command line tool that imports Pinboard data into Raindrop
Project-URL: Homepage, https://github.com/davep/paindrop
Project-URL: Repository, https://github.com/davep/paindrop
Project-URL: Documentation, https://github.com/davep/paindrop
Project-URL: Issues, https://github.com/davep/paindrop/issues
Author-email: Dave Pearson <davep@davep.org>
License:                     GNU GENERAL PUBLIC LICENSE
License-File: LICENSE
Keywords: bookmarking,cli,importer,importing,migration,pinboard,raindrop
Requires-Python: >=3.12
Requires-Dist: requests>=2.32.3
